restler/__init__.py
restler/response.py
restler/utils.py
restler/route.py
restler/errors.py
restler/core.py
restler/handlers/date_handler.py
restler/handlers/__init__.py
restler/handlers/json_handler.py
restler/handlers/form_handler.py
restler/handlers/url_handler.py
librestler-0.2.2.dist-info/WHEEL
librestler-0.2.2.dist-info/top_level.txt
librestler-0.2.2.dist-info/metadata.json
librestler-0.2.2.dist-info/METADATA
librestler-0.2.2.dist-info/RECORD
librestler-0.2.2.dist-info/DESCRIPTION.rst
