Metadata-Version: 2.0
Name: librestler
Version: 0.2.2
Summary: Object Oriented rest client
Home-page: http://jdost.us/restler/
Author: Jeff Ostendorf
Author-email: jostendorf@gmail.com
License: Apache 2.0
Platform: UNKNOWN
Classifier: Development Status :: 3 - Alpha
Classifier: Intended Audience :: Developers
Classifier: Natural Language :: English
Classifier: License :: OSI Approved :: Apache Software License
Classifier: Programming Language :: Python
Classifier: Programming Language :: Python :: 2.7
Classifier: Programming Language :: Python :: 3.2
Classifier: Programming Language :: Python :: 3.3
